{"nm":"Frame 2","v":"5.9.6","fr":60,"ip":0,"op":60,"w":100,"h":100,"ddd":0,"markers":[],"assets":[],"layers":[{"ty":3,"ind":65973,"hd":false,"nm":"Frame 2 - Null","st":0,"ip":0,"op":300,"bm":0,"ks":{"a":{"a":0,"k":[0,0]},"o":{"a":0,"k":100},"p":{"a":0,"k":[0,0]},"r":{"a":0,"k":0},"s":{"a":0,"k":[100,100]}}},{"ty":3,"ind":23260,"hd":false,"nm":"Group 5 - Null","st":0,"ip":0,"op":300,"bm":0,"ks":{"a":{"a":0,"k":[28,31]},"o":{"a":0,"k":100},"p":{"a":0,"k":[50,53]},"r":{"a":0,"k":0},"s":{"a":0,"k":[100,100]}},"parent":65973},{"ty":3,"ind":61556,"hd":false,"nm":"Group 3 - Null","st":0,"ip":0,"op":300,"bm":0,"ks":{"a":{"a":0,"k":[0,43]},"o":{"a":0,"k":100},"p":{"a":1,"k":[{"t":0,"s":[12,38],"o":{"x":[0.5],"y":[0.35]},"i":{"x":[0.15],"y":[1]},"ti":[0,0],"to":[0,0]},{"t":60,"s":[12,43]}]},"r":{"a":1,"k":[{"t":0,"s":[-8],"o":{"x":[0.5],"y":[0.35]},"i":{"x":[0.15],"y":[1]}},{"t":60,"s":[0]}]},"s":{"a":0,"k":[100,100]}},"parent":23260},{"ty":3,"ind":27849,"hd":false,"nm":"Vector 2 - Null","st":0,"ip":0,"op":300,"bm":0,"ks":{"a":{"a":0,"k":[0,0]},"o":{"a":0,"k":100},"p":{"a":0,"k":[32,0]},"r":{"a":0,"k":360},"s":{"a":0,"k":[-100,100]}},"parent":61556},{"ty":4,"ind":60729,"hd":false,"nm":"Frame 2 - Mask","st":0,"ip":0,"op":300,"bm":0,"ks":{"a":{"a":0,"k":[0,0]},"p":{"a":0,"k":[0,0]},"s":{"a":0,"k":[100,100]},"r":{"a":0,"k":0},"o":{"a":0,"k":100}},"shapes":[{"ty":"sh","nm":"Path","hd":false,"ks":{"a":0,"k":{"c":true,"v":[[0,100],[0,0],[100,0],[100,100],[0,100]],"i":[[0,0],[0,0],[0,0],[0,0],[0,0]],"o":[[0,0],[0,0],[0,0],[0,0],[0,0]]}}},{"ty":"fl","o":{"a":0,"k":100},"c":{"a":0,"k":[0,1,0]},"nm":"Fill","hd":false,"r":1}],"td":1,"parent":65973},{"ind":78594,"hd":false,"nm":"Vector 2 - Stroke","st":0,"ip":0,"op":300,"bm":0,"ks":{"a":{"a":0,"k":[0,0]},"p":{"a":0,"k":[0,0]},"s":{"a":0,"k":[100,100]},"r":{"a":0,"k":0},"o":{"a":0,"k":100}},"ty":4,"shapes":[{"ty":"sh","nm":"Path","hd":false,"ks":{"a":0,"k":{"c":false,"v":[[21.33333,0],[5.688890000000001,0],[8.881784197001252e-16,5.65116],[8.881784197001252e-16,27]],"i":[[0,0],[4.5511099999999995,0],[0,-1.8837199999999998],[0,-0.7325599999999994]],"o":[[-3.3185199999999995,0],[-4.55111,0],[0,18.08372],[0,0]]}}},{"ty":"st","o":{"a":0,"k":100},"w":{"a":0,"k":4},"c":{"a":0,"k":[0.25882352941176473,0.25882352941176473,0.25882352941176473]},"ml":0,"lc":2,"lj":1,"nm":"Stroke","hd":false}],"parent":27849,"tt":1},{"ty":3,"ind":18039,"hd":false,"nm":"Vector 1 - Null","st":0,"ip":0,"op":300,"bm":0,"ks":{"a":{"a":0,"k":[0,0]},"o":{"a":0,"k":100},"p":{"a":0,"k":[0,0]},"r":{"a":0,"k":0},"s":{"a":0,"k":[100,100]}},"parent":61556},{"ty":4,"ind":60729,"hd":false,"nm":"Frame 2 - Mask","st":0,"ip":0,"op":300,"bm":0,"ks":{"a":{"a":0,"k":[0,0]},"p":{"a":0,"k":[0,0]},"s":{"a":0,"k":[100,100]},"r":{"a":0,"k":0},"o":{"a":0,"k":100}},"shapes":[{"ty":"sh","nm":"Path","hd":false,"ks":{"a":0,"k":{"c":true,"v":[[0,100],[0,0],[100,0],[100,100],[0,100]],"i":[[0,0],[0,0],[0,0],[0,0],[0,0]],"o":[[0,0],[0,0],[0,0],[0,0],[0,0]]}}},{"ty":"fl","o":{"a":0,"k":100},"c":{"a":0,"k":[0,1,0]},"nm":"Fill","hd":false,"r":1}],"td":1,"parent":65973},{"ind":15611,"hd":false,"nm":"Vector 1 - Stroke","st":0,"ip":0,"op":300,"bm":0,"ks":{"a":{"a":0,"k":[0,0]},"p":{"a":0,"k":[0,0]},"s":{"a":0,"k":[100,100]},"r":{"a":0,"k":0},"o":{"a":0,"k":100}},"ty":4,"shapes":[{"ty":"sh","nm":"Path","hd":false,"ks":{"a":0,"k":{"c":false,"v":[[20.86957,0],[5.56522,0],[0,9],[0,43]],"i":[[0,0],[4.45218,0],[0,-3],[0,-1.1666700000000034]],"o":[[-3.2463799999999985,0],[-4.45217,0],[0,28.799999999999997],[0,0]]}}},{"ty":"st","o":{"a":0,"k":100},"w":{"a":0,"k":4},"c":{"a":0,"k":[0.25882352941176473,0.25882352941176473,0.25882352941176473]},"ml":0,"lc":2,"lj":1,"nm":"Stroke","hd":false}],"parent":18039,"tt":1},{"ty":3,"ind":6281,"hd":false,"nm":"Group 4 - Null","st":0,"ip":0,"op":300,"bm":0,"ks":{"a":{"a":0,"k":[0,0]},"o":{"a":0,"k":100},"p":{"a":1,"k":[{"t":0,"s":[0,26],"o":{"x":[0.5],"y":[0.35]},"i":{"x":[0.15],"y":[1]},"ti":[0,0],"to":[0,0]},{"t":60,"s":[0,20]}]},"r":{"a":0,"k":0},"s":{"a":0,"k":[100,100]}},"parent":23260},{"ty":3,"ind":96713,"hd":false,"nm":"Subtract - Null","st":0,"ip":0,"op":300,"bm":0,"ks":{"a":{"a":0,"k":[0,0]},"o":{"a":0,"k":100},"p":{"a":0,"k":[0,0]},"r":{"a":0,"k":0},"s":{"a":0,"k":[100,100]}},"parent":6281},{"ty":4,"ind":60729,"hd":false,"nm":"Frame 2 - Mask","st":0,"ip":0,"op":300,"bm":0,"ks":{"a":{"a":0,"k":[0,0]},"p":{"a":0,"k":[0,0]},"s":{"a":0,"k":[100,100]},"r":{"a":0,"k":0},"o":{"a":0,"k":100}},"shapes":[{"ty":"sh","nm":"Path","hd":false,"ks":{"a":0,"k":{"c":true,"v":[[0,100],[0,0],[100,0],[100,100],[0,100]],"i":[[0,0],[0,0],[0,0],[0,0],[0,0]],"o":[[0,0],[0,0],[0,0],[0,0],[0,0]]}}},{"ty":"fl","o":{"a":0,"k":100},"c":{"a":0,"k":[0,1,0]},"nm":"Fill","hd":false,"r":1}],"td":1,"parent":65973},{"ty":4,"ind":26931,"hd":false,"nm":"Subtract","st":0,"ip":0,"op":300,"bm":0,"ks":{"a":{"a":0,"k":[0,0]},"p":{"a":0,"k":[0,0]},"s":{"a":0,"k":[100,100]},"r":{"a":0,"k":0},"o":{"a":0,"k":100}},"shapes":[{"ty":"sh","nm":"Path","hd":false,"ks":{"a":0,"k":{"c":true,"v":[[6,0],[0,6],[0,36],[6,42],[50,42],[56,36],[56,6],[50,0],[6,0]],"i":[[0,0],[0,-3.31371],[0,0],[-3.31371,0],[0,0],[0,3.313699999999997],[0,0],[3.313699999999997,0],[0,0]],"o":[[-3.31371,0],[0,0],[0,3.313699999999997],[0,0],[3.313699999999997,0],[0,0],[0,-3.31371],[0,0],[0,0]]}}},{"ty":"sh","nm":"Path","hd":false,"ks":{"a":0,"k":{"c":true,"v":[[33,17.25],[30.4214,21.6256],[30.5,22.25],[30.5,27.25],[28,29.75],[25.5,27.25],[25.5,22.25],[25.5786,21.6256],[23,17.25],[28,12.25],[33,17.25],[33,17.25]],"i":[[0,0],[1.537700000000001,-0.8527999999999984],[0,-0.215600000000002],[0,0],[1.380700000000001,0],[0,1.380700000000001],[0,0],[-0.051300000000001234,0.19960000000000022],[0,1.8829999999999991],[-2.761400000000002,0],[0,-2.7614],[0,0]],"o":[[0,1.8829999999999991],[0.051300000000001234,0.19960000000000022],[0,0],[0,1.380700000000001],[-1.380700000000001,0],[0,0],[0,-0.21559999999999846],[-1.537700000000001,-0.8527999999999984],[0,-2.7614],[2.761400000000002,0],[0,0],[0,0]]}}},{"ty":"fl","o":{"a":0,"k":100},"c":{"a":0,"k":[0.25882352941176473,0.25882352941176473,0.25882352941176473]},"nm":"Fill","hd":false,"r":2}],"parent":96713,"ef":[],"tt":1}],"meta":{"a":"","d":"","tc":"","g":"Aninix"}}